{
  "type": "minecraft:crafting_shapeless",
  "category": "building",
  "ingredients": [
    {
      "item": "just-enought-building-blocks:corner_pillar_birch_leaves"
    },
    {
      "item": "just-enought-building-blocks:corner_pillar_birch_leaves"
    },
    {
      "item": "just-enought-building-blocks:corner_pillar_birch_leaves"
    },
    {
      "item": "just-enought-building-blocks:corner_pillar_birch_leaves"
    }
  ],
  "result": {
    "count": 1,
    "id": "minecraft:birch_leaves"
  }
}