{
  "type": "minecraft:crafting_shapeless",
  "category": "building",
  "ingredients": [
    {
      "item": "just-enought-building-blocks:corner_pillar_polished_deepslate"
    },
    {
      "item": "just-enought-building-blocks:corner_pillar_polished_deepslate"
    },
    {
      "item": "just-enought-building-blocks:corner_pillar_polished_deepslate"
    },
    {
      "item": "just-enought-building-blocks:corner_pillar_polished_deepslate"
    }
  ],
  "result": {
    "count": 1,
    "id": "minecraft:polished_deepslate"
  }
}