{
  "variants": {
    "type=bottom,waterlogged=false": {
      "model": "just-enought-building-blocks:block/slab_smooth_basalt_bottom"
    },
    "type=bottom,waterlogged=true": {
      "model": "just-enought-building-blocks:block/slab_smooth_basalt_bottom"
    },
    "type=double,waterlogged=false": {
      "model": "minecraft:block/smooth_basalt"
    },
    "type=double,waterlogged=true": {
      "model": "minecraft:block/smooth_basalt"
    },
    "type=top,waterlogged=false": {
      "model": "just-enought-building-blocks:block/slab_smooth_basalt_top"
    },
    "type=top,waterlogged=true": {
      "model": "just-enought-building-blocks:block/slab_smooth_basalt_top"
    }
  }
}