{
  "variants": {
    "type=bottom,waterlogged=false": {
      "model": "just-enought-building-blocks:block/slab_chiseled_tuff_bottom"
    },
    "type=bottom,waterlogged=true": {
      "model": "just-enought-building-blocks:block/slab_chiseled_tuff_bottom"
    },
    "type=double,waterlogged=false": {
      "model": "minecraft:block/chiseled_tuff"
    },
    "type=double,waterlogged=true": {
      "model": "minecraft:block/chiseled_tuff"
    },
    "type=top,waterlogged=false": {
      "model": "just-enought-building-blocks:block/slab_chiseled_tuff_top"
    },
    "type=top,waterlogged=true": {
      "model": "just-enought-building-blocks:block/slab_chiseled_tuff_top"
    }
  }
}